bootycontrol/__init__.py
bootycontrol/__main__.py
bootycontrol/version.py
bootycontrol-0.0.1.dist-info/DESCRIPTION.rst
bootycontrol-0.0.1.dist-info/METADATA
bootycontrol-0.0.1.dist-info/RECORD
bootycontrol-0.0.1.dist-info/WHEEL
bootycontrol-0.0.1.dist-info/entry_points.txt
bootycontrol-0.0.1.dist-info/metadata.json
bootycontrol-0.0.1.dist-info/top_level.txt
